pylite/Chart.py
pylite/__init__.py
pylite/scripts/chart.js
pylite/scripts/lightweight-charts.standalone.js
pylite/scripts/lightweight_chart.html
pylitechart-0.1.0.dist-info/LICENSE
pylitechart-0.1.0.dist-info/METADATA
pylitechart-0.1.0.dist-info/WHEEL
pylitechart-0.1.0.dist-info/top_level.txt
pylitechart-0.1.0.dist-info/RECORD
