Metadata-Version: 2.1
Name: pylitechart
Version: 0.1.0
Summary: A minimal lightweight-charts PySide6 wrapper
Author: ursamir
Author-email: samir.nmiet@gmail.com
Classifier: Programming Language :: Python :: 3
Classifier: License :: OSI Approved :: MIT License
Classifier: Operating System :: OS Independent
Requires-Python: >=3.6
License-File: LICENSE
Requires-Dist: PySide6
Requires-Dist: PyQtWebEngine
